jsonata/__init__.py
jsonata/constants.py
jsonata/datetimeutils.py
jsonata/functions.py
jsonata/jexception.py
jsonata/jsonata.py
jsonata/parser.py
jsonata/signature.py
jsonata/timebox.py
jsonata/tokenizer.py
jsonata/utils.py
jsonata/cli/__init__.py
jsonata/cli/__main__.py
jsonata_python-0.6.0.dist-info/METADATA
jsonata_python-0.6.0.dist-info/WHEEL
jsonata_python-0.6.0.dist-info/licenses/LICENSE
jsonata_python-0.6.0.dist-info/RECORD
