Metadata-Version: 2.4
Name: jsonata-python
Version: 0.6.0
Summary: Pure Python implementation of JSONata
Project-URL: Homepage, https://github.com/rayokota/jsonata-python
Project-URL: Bug Reports, https://github.com/rayokota/jsonata-python/issues
Author: Robert Yokota
License: Apache License
License-File: LICENSE
Keywords: json,jsonata
Classifier: Development Status :: 4 - Beta
Classifier: License :: OSI Approved :: Apache Software License
Classifier: Programming Language :: Python
Requires-Python: >=3.9
